{
  "id": "rspx0v",
  "levelNumber": 32,
  "difficulty": "medium",
  "difficultyRating": 5,
  "name": "Generiert (medium)",
  "cages": [
    {
      "id": "x86i2e",
      "cells": [
        {
          "row": 0,
          "col": 0
        },
        {
          "row": 0,
          "col": 1
        }
      ],
      "sum": 9,
      "color": "blue.100"
    },
    {
      "id": "m90rou",
      "cells": [
        {
          "row": 0,
          "col": 2
        },
        {
          "row": 0,
          "col": 3
        }
      ],
      "sum": 3,
      "color": "green.100"
    },
    {
      "id": "ujbd18",
      "cells": [
        {
          "row": 0,
          "col": 4
        },
        {
          "row": 0,
          "col": 5
        }
      ],
      "sum": 15,
      "color": "blue.100"
    },
    {
      "id": "7mg4nn",
      "cells": [
        {
          "row": 0,
          "col": 6
        },
        {
          "row": 0,
          "col": 7
        }
      ],
      "sum": 15,
      "color": "green.100"
    },
    {
      "id": "7rvhgw",
      "cells": [
        {
          "row": 0,
          "col": 8
        },
        {
          "row": 1,
          "col": 8
        }
      ],
      "sum": 9,
      "color": "blue.100"
    },
    {
      "id": "hvfkf5",
      "cells": [
        {
          "row": 3,
          "col": 7
        },
        {
          "row": 4,
          "col": 7
        }
      ],
      "sum": 3,
      "color": "blue.100"
    },
    {
      "id": "gj0z7j",
      "cells": [
        {
          "row": 4,
          "col": 1
        },
        {
          "row": 4,
          "col": 2
        }
      ],
      "sum": 4,
      "color": "blue.100"
    },
    {
      "id": "plq627",
      "cells": [
        {
          "row": 2,
          "col": 4
        },
        {
          "row": 3,
          "col": 4
        }
      ],
      "sum": 17,
      "color": "blue.100"
    },
    {
      "id": "ub0g53",
      "cells": [
        {
          "row": 6,
          "col": 5
        },
        {
          "row": 6,
          "col": 4
        },
        {
          "row": 7,
          "col": 4
        }
      ],
      "sum": 16,
      "color": "blue.100"
    },
    {
      "id": "auob5e",
      "cells": [
        {
          "row": 1,
          "col": 3
        },
        {
          "row": 1,
          "col": 4
        },
        {
          "row": 1,
          "col": 2
        }
      ],
      "sum": 20,
      "color": "pink.100"
    },
    {
      "id": "zzzxte",
      "cells": [
        {
          "row": 2,
          "col": 2
        },
        {
          "row": 2,
          "col": 1
        },
        {
          "row": 3,
          "col": 1
        }
      ],
      "sum": 11,
      "color": "green.100"
    },
    {
      "id": "onygoy",
      "cells": [
        {
          "row": 8,
          "col": 0
        },
        {
          "row": 7,
          "col": 0
        },
        {
          "row": 6,
          "col": 0
        },
        {
          "row": 6,
          "col": 1
        },
        {
          "row": 6,
          "col": 2
        }
      ],
      "sum": 17,
      "color": "blue.100"
    },
    {
      "id": "v3lini",
      "cells": [
        {
          "row": 3,
          "col": 6
        },
        {
          "row": 2,
          "col": 6
        }
      ],
      "sum": 5,
      "color": "green.100"
    },
    {
      "id": "4a9muy",
      "cells": [
        {
          "row": 1,
          "col": 0
        },
        {
          "row": 1,
          "col": 1
        }
      ],
      "sum": 11,
      "color": "yellow.100"
    },
    {
      "id": "3799y2",
      "cells": [
        {
          "row": 8,
          "col": 1
        },
        {
          "row": 7,
          "col": 1
        }
      ],
      "sum": 14,
      "color": "green.100"
    },
    {
      "id": "v0peot",
      "cells": [
        {
          "row": 4,
          "col": 8
        },
        {
          "row": 5,
          "col": 8
        },
        {
          "row": 5,
          "col": 7
        }
      ],
      "sum": 23,
      "color": "green.100"
    },
    {
      "id": "kkb8a6",
      "cells": [
        {
          "row": 4,
          "col": 6
        },
        {
          "row": 4,
          "col": 5
        },
        {
          "row": 5,
          "col": 5
        }
      ],
      "sum": 14,
      "color": "pink.100"
    },
    {
      "id": "fmpzka",
      "cells": [
        {
          "row": 3,
          "col": 8
        },
        {
          "row": 2,
          "col": 8
        },
        {
          "row": 2,
          "col": 7
        },
        {
          "row": 1,
          "col": 7
        },
        {
          "row": 1,
          "col": 6
        }
      ],
      "sum": 26,
      "color": "pink.100"
    },
    {
      "id": "ln8se3",
      "cells": [
        {
          "row": 7,
          "col": 5
        },
        {
          "row": 7,
          "col": 6
        },
        {
          "row": 7,
          "col": 7
        }
      ],
      "sum": 15,
      "color": "green.100"
    },
    {
      "id": "ozcqoo",
      "cells": [
        {
          "row": 8,
          "col": 6
        },
        {
          "row": 8,
          "col": 7
        }
      ],
      "sum": 16,
      "color": "blue.100"
    },
    {
      "id": "eyhkpi",
      "cells": [
        {
          "row": 6,
          "col": 8
        },
        {
          "row": 6,
          "col": 7
        }
      ],
      "sum": 9,
      "color": "blue.100"
    },
    {
      "id": "ra5vi0",
      "cells": [
        {
          "row": 3,
          "col": 0
        },
        {
          "row": 2,
          "col": 0
        },
        {
          "row": 4,
          "col": 0
        },
        {
          "row": 5,
          "col": 0
        }
      ],
      "sum": 30,
      "color": "pink.100"
    },
    {
      "id": "p9q54h",
      "cells": [
        {
          "row": 7,
          "col": 8
        },
        {
          "row": 8,
          "col": 8
        }
      ],
      "sum": 3,
      "color": "pink.100"
    },
    {
      "id": "u1pxhd",
      "cells": [
        {
          "row": 5,
          "col": 1
        },
        {
          "row": 5,
          "col": 2
        }
      ],
      "sum": 12,
      "color": "green.100"
    },
    {
      "id": "clnzmr",
      "cells": [
        {
          "row": 1,
          "col": 5
        },
        {
          "row": 2,
          "col": 5
        },
        {
          "row": 3,
          "col": 5
        }
      ],
      "sum": 9,
      "color": "yellow.100"
    },
    {
      "id": "e3dv7y",
      "cells": [
        {
          "row": 4,
          "col": 3
        },
        {
          "row": 3,
          "col": 3
        },
        {
          "row": 4,
          "col": 4
        },
        {
          "row": 5,
          "col": 4
        }
      ],
      "sum": 21,
      "color": "green.100"
    },
    {
      "id": "7x9ltq",
      "cells": [
        {
          "row": 6,
          "col": 3
        },
        {
          "row": 5,
          "col": 3
        },
        {
          "row": 7,
          "col": 3
        },
        {
          "row": 8,
          "col": 3
        }
      ],
      "sum": 18,
      "color": "pink.100"
    },
    {
      "id": "jrwllu",
      "cells": [
        {
          "row": 7,
          "col": 2
        },
        {
          "row": 8,
          "col": 2
        }
      ],
      "sum": 14,
      "color": "yellow.100"
    },
    {
      "id": "yb2vnn",
      "cells": [
        {
          "row": 5,
          "col": 6
        },
        {
          "row": 6,
          "col": 6
        }
      ],
      "sum": 10,
      "color": "yellow.100"
    },
    {
      "id": "wljzal",
      "cells": [
        {
          "row": 2,
          "col": 3
        }
      ],
      "sum": 4,
      "color": "yellow.100"
    },
    {
      "id": "eqenwl",
      "cells": [
        {
          "row": 3,
          "col": 2
        }
      ],
      "sum": 4,
      "color": "pink.100"
    },
    {
      "id": "ra5y90",
      "cells": [
        {
          "row": 8,
          "col": 4
        },
        {
          "row": 8,
          "col": 5
        }
      ],
      "sum": 8,
      "color": "yellow.100"
    }
  ],
  "initialValues": [
    [
      0,
      0,
      0,
      0,
      6,
      9,
      7,
      0,
      0
    ],
    [
      0,
      0,
      0,
      0,
      0,
      0,
      0,
      4,
      0
    ],
    [
      0,
      0,
      0,
      0,
      0,
      0,
      0,
      0,
      0
    ],
    [
      0,
      0,
      0,
      0,
      0,
      0,
      3,
      1,
      0
    ],
    [
      0,
      0,
      0,
      0,
      0,
      0,
      0,
      0,
      8
    ],
    [
      0,
      0,
      0,
      0,
      0,
      2,
      0,
      0,
      0
    ],
    [
      0,
      0,
      0,
      0,
      0,
      0,
      0,
      0,
      0
    ],
    [
      0,
      0,
      0,
      0,
      0,
      0,
      0,
      0,
      0
    ],
    [
      0,
      0,
      0,
      0,
      0,
      0,
      9,
      0,
      0
    ]
  ],
  "solution": [
    [
      5,
      4,
      1,
      2,
      6,
      9,
      7,
      8,
      3
    ],
    [
      2,
      9,
      8,
      7,
      5,
      3,
      1,
      4,
      6
    ],
    [
      7,
      3,
      6,
      4,
      8,
      1,
      2,
      9,
      5
    ],
    [
      6,
      2,
      4,
      8,
      9,
      5,
      3,
      1,
      7
    ],
    [
      9,
      1,
      3,
      6,
      4,
      7,
      5,
      2,
      8
    ],
    [
      8,
      5,
      7,
      1,
      3,
      2,
      4,
      6,
      9
    ],
    [
      3,
      7,
      2,
      9,
      1,
      8,
      6,
      5,
      4
    ],
    [
      1,
      6,
      9,
      5,
      7,
      4,
      8,
      3,
      2
    ],
    [
      4,
      8,
      5,
      3,
      2,
      6,
      9,
      7,
      1
    ]
  ],
  "author": "generator",
  "createdAt": "2026-07-24T06:16:55.288Z",
  "updatedAt": "2026-07-24T06:16:55.288Z"
}
