{
  "id": "uqt3ah",
  "levelNumber": 25,
  "difficultyRating": 4,
  "name": "Einfach Adventure 25",
  "cages": [
    {
      "id": "ohgukw",
      "cells": [
        {
          "row": 7,
          "col": 2
        },
        {
          "row": 6,
          "col": 2
        },
        {
          "row": 8,
          "col": 2
        }
      ],
      "sum": 15,
      "color": "blue.100"
    },
    {
      "id": "3dxd6j",
      "cells": [
        {
          "row": 3,
          "col": 2
        },
        {
          "row": 4,
          "col": 2
        },
        {
          "row": 4,
          "col": 1
        }
      ],
      "sum": 17,
      "color": "yellow.100"
    },
    {
      "id": "h1e43v",
      "cells": [
        {
          "row": 1,
          "col": 6
        },
        {
          "row": 1,
          "col": 7
        }
      ],
      "sum": 3,
      "color": "yellow.100"
    },
    {
      "id": "8bvk8r",
      "cells": [
        {
          "row": 3,
          "col": 8
        }
      ],
      "sum": 1,
      "color": "pink.100"
    },
    {
      "id": "7eed1o",
      "cells": [
        {
          "row": 0,
          "col": 5
        },
        {
          "row": 0,
          "col": 4
        },
        {
          "row": 0,
          "col": 6
        }
      ],
      "sum": 18,
      "color": "blue.100"
    },
    {
      "id": "so7k00",
      "cells": [
        {
          "row": 2,
          "col": 1
        },
        {
          "row": 1,
          "col": 1
        }
      ],
      "sum": 13,
      "color": "yellow.100"
    },
    {
      "id": "i883g0",
      "cells": [
        {
          "row": 1,
          "col": 4
        },
        {
          "row": 1,
          "col": 5
        },
        {
          "row": 1,
          "col": 3
        }
      ],
      "sum": 24,
      "color": "pink.100"
    },
    {
      "id": "d3ulpo",
      "cells": [
        {
          "row": 7,
          "col": 0
        },
        {
          "row": 6,
          "col": 0
        },
        {
          "row": 5,
          "col": 0
        }
      ],
      "sum": 17,
      "color": "blue.100"
    },
    {
      "id": "s93fsj",
      "cells": [
        {
          "row": 7,
          "col": 4
        }
      ],
      "sum": 1,
      "color": "yellow.100"
    },
    {
      "id": "immdsm",
      "cells": [
        {
          "row": 7,
          "col": 3
        }
      ],
      "sum": 9,
      "color": "pink.100"
    },
    {
      "id": "a1fv95",
      "cells": [
        {
          "row": 3,
          "col": 4
        }
      ],
      "sum": 6,
      "color": "green.100"
    },
    {
      "id": "17e468",
      "cells": [
        {
          "row": 6,
          "col": 4
        },
        {
          "row": 6,
          "col": 5
        },
        {
          "row": 5,
          "col": 5
        }
      ],
      "sum": 19,
      "color": "blue.100"
    },
    {
      "id": "haja0w",
      "cells": [
        {
          "row": 4,
          "col": 3
        },
        {
          "row": 3,
          "col": 3
        }
      ],
      "sum": 13,
      "color": "pink.100"
    },
    {
      "id": "mbwhqm",
      "cells": [
        {
          "row": 7,
          "col": 6
        },
        {
          "row": 8,
          "col": 6
        },
        {
          "row": 8,
          "col": 5
        }
      ],
      "sum": 14,
      "color": "blue.100"
    },
    {
      "id": "8ua8f4",
      "cells": [
        {
          "row": 8,
          "col": 1
        },
        {
          "row": 8,
          "col": 0
        }
      ],
      "sum": 10,
      "color": "pink.100"
    },
    {
      "id": "0j1i4s",
      "cells": [
        {
          "row": 2,
          "col": 3
        },
        {
          "row": 2,
          "col": 2
        },
        {
          "row": 2,
          "col": 4
        }
      ],
      "sum": 12,
      "color": "blue.100"
    },
    {
      "id": "uvo3ve",
      "cells": [
        {
          "row": 7,
          "col": 5
        }
      ],
      "sum": 2,
      "color": "pink.100"
    },
    {
      "id": "9vkzz5",
      "cells": [
        {
          "row": 8,
          "col": 4
        },
        {
          "row": 8,
          "col": 3
        }
      ],
      "sum": 7,
      "color": "green.100"
    },
    {
      "id": "aoqn8s",
      "cells": [
        {
          "row": 8,
          "col": 8
        },
        {
          "row": 8,
          "col": 7
        }
      ],
      "sum": 15,
      "color": "pink.100"
    },
    {
      "id": "oy8iau",
      "cells": [
        {
          "row": 4,
          "col": 7
        },
        {
          "row": 5,
          "col": 7
        },
        {
          "row": 4,
          "col": 8
        }
      ],
      "sum": 13,
      "color": "blue.100"
    },
    {
      "id": "y990v3",
      "cells": [
        {
          "row": 5,
          "col": 4
        }
      ],
      "sum": 3,
      "color": "pink.100"
    },
    {
      "id": "bazlti",
      "cells": [
        {
          "row": 2,
          "col": 6
        },
        {
          "row": 3,
          "col": 6
        },
        {
          "row": 3,
          "col": 5
        }
      ],
      "sum": 19,
      "color": "blue.100"
    },
    {
      "id": "zgmzfc",
      "cells": [
        {
          "row": 3,
          "col": 0
        }
      ],
      "sum": 2,
      "color": "blue.100"
    },
    {
      "id": "04g4vz",
      "cells": [
        {
          "row": 6,
          "col": 3
        }
      ],
      "sum": 6,
      "color": "yellow.100"
    },
    {
      "id": "e8e05h",
      "cells": [
        {
          "row": 5,
          "col": 2
        },
        {
          "row": 5,
          "col": 1
        },
        {
          "row": 6,
          "col": 1
        }
      ],
      "sum": 14,
      "color": "pink.100"
    },
    {
      "id": "2zgkrs",
      "cells": [
        {
          "row": 7,
          "col": 8
        },
        {
          "row": 6,
          "col": 8
        },
        {
          "row": 7,
          "col": 7
        }
      ],
      "sum": 11,
      "color": "yellow.100"
    },
    {
      "id": "41752e",
      "cells": [
        {
          "row": 4,
          "col": 6
        }
      ],
      "sum": 2,
      "color": "pink.100"
    },
    {
      "id": "uifr6g",
      "cells": [
        {
          "row": 1,
          "col": 2
        },
        {
          "row": 0,
          "col": 2
        },
        {
          "row": 0,
          "col": 3
        }
      ],
      "sum": 13,
      "color": "green.100"
    },
    {
      "id": "1oghmt",
      "cells": [
        {
          "row": 5,
          "col": 6
        }
      ],
      "sum": 5,
      "color": "yellow.100"
    },
    {
      "id": "2on0y8",
      "cells": [
        {
          "row": 3,
          "col": 1
        }
      ],
      "sum": 3,
      "color": "pink.100"
    },
    {
      "id": "simq8e",
      "cells": [
        {
          "row": 4,
          "col": 4
        },
        {
          "row": 4,
          "col": 5
        }
      ],
      "sum": 10,
      "color": "yellow.100"
    },
    {
      "id": "76k2sv",
      "cells": [
        {
          "row": 6,
          "col": 6
        }
      ],
      "sum": 9,
      "color": "pink.100"
    },
    {
      "id": "dnjhcl",
      "cells": [
        {
          "row": 0,
          "col": 7
        },
        {
          "row": 0,
          "col": 8
        }
      ],
      "sum": 17,
      "color": "pink.100"
    },
    {
      "id": "etksgu",
      "cells": [
        {
          "row": 2,
          "col": 5
        }
      ],
      "sum": 3,
      "color": "yellow.100"
    },
    {
      "id": "ktyf3d",
      "cells": [
        {
          "row": 2,
          "col": 7
        }
      ],
      "sum": 5,
      "color": "pink.100"
    },
    {
      "id": "ggf5pi",
      "cells": [
        {
          "row": 2,
          "col": 8
        }
      ],
      "sum": 6,
      "color": "blue.100"
    },
    {
      "id": "hmnj9w",
      "cells": [
        {
          "row": 2,
          "col": 0
        },
        {
          "row": 1,
          "col": 0
        },
        {
          "row": 0,
          "col": 0
        }
      ],
      "sum": 12,
      "color": "pink.100"
    },
    {
      "id": "oxb922",
      "cells": [
        {
          "row": 0,
          "col": 1
        }
      ],
      "sum": 2,
      "color": "blue.100"
    },
    {
      "id": "pdshe1",
      "cells": [
        {
          "row": 1,
          "col": 8
        }
      ],
      "sum": 3,
      "color": "green.100"
    },
    {
      "id": "zn2ww7",
      "cells": [
        {
          "row": 3,
          "col": 7
        }
      ],
      "sum": 9,
      "color": "yellow.100"
    },
    {
      "id": "rdjth3",
      "cells": [
        {
          "row": 4,
          "col": 0
        }
      ],
      "sum": 5,
      "color": "pink.100"
    },
    {
      "id": "sjb0g4",
      "cells": [
        {
          "row": 5,
          "col": 3
        }
      ],
      "sum": 2,
      "color": "blue.100"
    },
    {
      "id": "zguk3z",
      "cells": [
        {
          "row": 5,
          "col": 8
        }
      ],
      "sum": 7,
      "color": "pink.100"
    },
    {
      "id": "3wnhoj",
      "cells": [
        {
          "row": 6,
          "col": 7
        }
      ],
      "sum": 1,
      "color": "green.100"
    },
    {
      "id": "7pe194",
      "cells": [
        {
          "row": 7,
          "col": 1
        }
      ],
      "sum": 7,
      "color": "yellow.100"
    }
  ],
  "initialValues": [
    [
      0,
      0,
      3,
      0,
      0,
      6,
      7,
      0,
      9
    ],
    [
      4,
      5,
      6,
      0,
      0,
      0,
      0,
      0,
      0
    ],
    [
      7,
      0,
      0,
      0,
      0,
      0,
      4,
      0,
      0
    ],
    [
      0,
      0,
      4,
      0,
      0,
      7,
      0,
      0,
      0
    ],
    [
      0,
      0,
      0,
      8,
      0,
      0,
      0,
      0,
      4
    ],
    [
      8,
      0,
      1,
      0,
      0,
      0,
      0,
      0,
      0
    ],
    [
      0,
      0,
      0,
      0,
      0,
      0,
      0,
      0,
      0
    ],
    [
      0,
      0,
      8,
      0,
      0,
      0,
      3,
      0,
      0
    ],
    [
      9,
      0,
      0,
      3,
      0,
      0,
      0,
      0,
      0
    ]
  ],
  "solution": [
    [
      1,
      2,
      3,
      4,
      5,
      6,
      7,
      8,
      9
    ],
    [
      4,
      5,
      6,
      7,
      8,
      9,
      1,
      2,
      3
    ],
    [
      7,
      8,
      9,
      1,
      2,
      3,
      4,
      5,
      6
    ],
    [
      2,
      3,
      4,
      5,
      6,
      7,
      8,
      9,
      1
    ],
    [
      5,
      6,
      7,
      8,
      9,
      1,
      2,
      3,
      4
    ],
    [
      8,
      9,
      1,
      2,
      3,
      4,
      5,
      6,
      7
    ],
    [
      3,
      4,
      5,
      6,
      7,
      8,
      9,
      1,
      2
    ],
    [
      6,
      7,
      8,
      9,
      1,
      2,
      3,
      4,
      5
    ],
    [
      9,
      1,
      2,
      3,
      4,
      5,
      6,
      7,
      8
    ]
  ],
  "description": "Ein Level (Schwierigkeit 4/10) mit 45 Käfigen.",
  "author": "KillerSudoku Generator",
  "createdAt": "2025-05-03T00:29:51.961Z"
}